[
  {
    "appointmentId": 67480,
    "patientId": 311322,
    "startDate": "03/03/2014  1:00PM",
    "endDate": "03/03/2014  2:00PM",
    "resourceName": "Adkins MD, Stanley",
    "description": "account, test",
    "status": "Confirmed",
    "insertUserId": "!blake",
    "insertDate": "03/03/2014 12:12PM",
    "updateUserId": "!blake",
    "updateDate": "03/03/2014 12:13PM",
    "comments": null,
    "referralNumber": null,
    "chiefComplaint": "<li>Standard Service:<ul><li>801096 - DS: Inhouse DOT</ul><li>Optional Services<ul><li>82705 - Breath Alcohol Test<li>99070-D9 - MRO Fee</ul>",
    "claimId": null,
    "type": "DOTS and Random D/S",
    "cancelComment": null,
    "walkIn": null,
    "serviceLocationName": "Adkins Medical Group",
    "referringName": null
  },
  {
    "appointmentId": 67554,
    "patientId": 311322,
    "startDate": "05/21/2014  2:00PM",
    "endDate": "05/21/2014  2:20PM",
    "resourceName": "Marcus Welby",
    "description": "account, test",
    "status": "Scheduled",
    "insertUserId": "!chilln",
    "insertDate": "05/20/2014  4:12PM",
    "updateUserId": "!chilln",
    "updateDate": "05/20/2014  4:12PM",
    "comments": "",
    "referralNumber": "",
    "chiefComplaint": "",
    "claimId": null,
    "type": "20 Min Slot",
    "cancelComment": null,
    "walkIn": null,
    "serviceLocationName": "iSALUS Healthcare",
    "referringName": null
  },
  {
    "appointmentId": 68808,
    "patientId": 311322,
    "startDate": "08/18/2015  3:45PM",
    "endDate": "08/18/2015  4:00PM",
    "resourceName": "Brooks MD, Kristi F.",
    "description": "Walk-In",
    "status": "Checked-In",
    "insertUserId": "!andy",
    "insertDate": "08/18/2015  3:48PM",
    "updateUserId": "!andy",
    "updateDate": "08/18/2015  3:48PM",
    "comments": null,
    "referralNumber": null,
    "chiefComplaint": "",
    "claimId": 29324,
    "type": null,
    "cancelComment": null,
    "walkIn": null,
    "serviceLocationName": "Sisselman Medical Group",
    "referringName": null
  },
  {
    "appointmentId": 68809,
    "patientId": 311322,
    "startDate": "08/18/2015  3:55PM",
    "endDate": "08/18/2015  4:10PM",
    "resourceName": "Brooks MD, Kristi F.",
    "description": "Walk-In",
    "status": "Checked-In",
    "insertUserId": "!andy",
    "insertDate": "08/18/2015  3:55PM",
    "updateUserId": "!andy",
    "updateDate": "08/18/2015  3:55PM",
    "comments": null,
    "referralNumber": null,
    "chiefComplaint": "",
    "claimId": 29325,
    "type": null,
    "cancelComment": null,
    "walkIn": null,
    "serviceLocationName": "Sisselman Medical Group",
    "referringName": null
  },
  {
    "appointmentId": 68810,
    "patientId": 311322,
    "startDate": "08/19/2015  9:45AM",
    "endDate": "08/19/2015 10:00AM",
    "resourceName": "Brooks MD, Kristi F.",
    "description": "Walk-In",
    "status": "Checked-In",
    "insertUserId": "!andy",
    "insertDate": "08/19/2015  9:46AM",
    "updateUserId": "!andy",
    "updateDate": "08/19/2015  9:46AM",
    "comments": null,
    "referralNumber": null,
    "chiefComplaint": "",
    "claimId": 29326,
    "type": null,
    "cancelComment": null,
    "walkIn": null,
    "serviceLocationName": "Sisselman Medical Group",
    "referringName": null
  },
  {
    "appointmentId": 69866,
    "patientId": 311322,
    "startDate": "07/25/2016  6:00PM",
    "endDate": "07/25/2016  6:10PM",
    "resourceName": "Adkins MD, Stanley",
    "description": "account, test",
    "status": "Scheduled",
    "insertUserId": "!adam",
    "insertDate": "07/25/2016  5:32PM",
    "updateUserId": "!adam",
    "updateDate": "07/25/2016  5:32PM",
    "comments": null,
    "referralNumber": null,
    "chiefComplaint": null,
    "claimId": null,
    "type": "15 Min Slot",
    "cancelComment": null,
    "walkIn": null,
    "serviceLocationName": "Adkins Medical Group",
    "referringName": null
  },
  {
    "appointmentId": 70029,
    "patientId": 311322,
    "startDate": "03/20/2017  7:15AM",
    "endDate": "03/20/2017  7:35AM",
    "resourceName": "Smith MD, Maria N.",
    "description": "Alcoholics anonymous (AA)",
    "status": "Checked-In",
    "insertUserId": "!blake",
    "insertDate": "03/20/2017  9:51AM",
    "updateUserId": "!blake",
    "updateDate": "03/20/2017  9:57AM",
    "comments": null,
    "referralNumber": null,
    "chiefComplaint": null,
    "claimId": null,
    "type": "Health Screen",
    "cancelComment": null,
    "walkIn": null,
    "serviceLocationName": "iSALUS Healthcare",
    "referringName": null
  },
  {
    "appointmentId": 70032,
    "patientId": 311322,
    "startDate": "03/21/2017  7:15AM",
    "endDate": "03/21/2017  7:35AM",
    "resourceName": "Smith MD, Maria N.",
    "description": null,
    "status": "Checked-In",
    "insertUserId": "!blake",
    "insertDate": "03/20/2017  9:52AM",
    "updateUserId": "!blake",
    "updateDate": "03/20/2017  9:57AM",
    "comments": null,
    "referralNumber": null,
    "chiefComplaint": null,
    "claimId": null,
    "type": "Health Screen",
    "cancelComment": null,
    "walkIn": null,
    "serviceLocationName": "iSALUS Healthcare",
    "referringName": null
  },
  {
    "appointmentId": 70035,
    "patientId": 311322,
    "startDate": "03/22/2017  7:15AM",
    "endDate": "03/22/2017  7:35AM",
    "resourceName": "Smith MD, Maria N.",
    "description": null,
    "status": "Scheduled",
    "insertUserId": "!blake",
    "insertDate": "03/20/2017  9:52AM",
    "updateUserId": "!blake",
    "updateDate": "03/20/2017  9:52AM",
    "comments": null,
    "referralNumber": null,
    "chiefComplaint": null,
    "claimId": null,
    "type": "Health Screen",
    "cancelComment": null,
    "walkIn": null,
    "serviceLocationName": "Celadon Corporate",
    "referringName": null
  },
  {
    "appointmentId": 70038,
    "patientId": 311322,
    "startDate": "03/23/2017  7:15AM",
    "endDate": "03/23/2017  7:35AM",
    "resourceName": "Smith MD, Maria N.",
    "description": null,
    "status": "Scheduled",
    "insertUserId": "!blake",
    "insertDate": "03/20/2017  9:52AM",
    "updateUserId": "!blake",
    "updateDate": "03/20/2017  9:52AM",
    "comments": null,
    "referralNumber": null,
    "chiefComplaint": null,
    "claimId": null,
    "type": "Health Screen",
    "cancelComment": null,
    "walkIn": null,
    "serviceLocationName": "Celadon Corporate",
    "referringName": null
  },
  {
    "appointmentId": 71369,
    "patientId": 311322,
    "startDate": "07/20/2017 12:00AM",
    "endDate": "07/20/2017 12:15AM",
    "resourceName": "Adkins MD, Stanley",
    "description": "Walk-In",
    "status": "Checked-In",
    "insertUserId": "!adam",
    "insertDate": "07/20/2017 10:54AM",
    "updateUserId": "!adam",
    "updateDate": "07/20/2017 10:54AM",
    "comments": null,
    "referralNumber": null,
    "chiefComplaint": "",
    "claimId": 29551,
    "type": null,
    "cancelComment": null,
    "walkIn": null,
    "serviceLocationName": "Carly\u0027s Test Location",
    "referringName": null
  },
  {
    "appointmentId": 71646,
    "patientId": 311322,
    "startDate": "12/11/2017 12:00PM",
    "endDate": "12/11/2017 12:40PM",
    "resourceName": "Adkins MD, Stanley",
    "description": "account, test",
    "status": "Scheduled",
    "insertUserId": "!austin",
    "insertDate": "12/12/2017 11:00AM",
    "updateUserId": "!austin",
    "updateDate": "12/12/2017 11:00AM",
    "comments": null,
    "referralNumber": null,
    "chiefComplaint": null,
    "claimId": 29802,
    "type": "CDL Exam",
    "cancelComment": null,
    "walkIn": null,
    "serviceLocationName": null,
    "referringName": null
  },
  {
    "appointmentId": 71671,
    "patientId": 311322,
    "startDate": "01/25/2018  5:00PM",
    "endDate": "01/25/2018  5:30PM",
    "resourceName": "Adkins MD, Stanley",
    "description": "account, test",
    "status": "Confirmed",
    "insertUserId": "!awade",
    "insertDate": "01/24/2018  1:50PM",
    "updateUserId": "!awade",
    "updateDate": "01/24/2018  1:51PM",
    "comments": null,
    "referralNumber": null,
    "chiefComplaint": null,
    "claimId": null,
    "type": "Physical - 30 minutes",
    "cancelComment": null,
    "walkIn": null,
    "serviceLocationName": "Adkins Medical Group",
    "referringName": null
  },
  {
    "appointmentId": 71680,
    "patientId": 311322,
    "startDate": "01/26/2018  4:15PM",
    "endDate": "01/26/2018  4:35PM",
    "resourceName": "Adkins MD, Stanley",
    "description": "account, test",
    "status": "Carlys Status",
    "insertUserId": "brad",
    "insertDate": "01/24/2018  1:53PM",
    "updateUserId": "brad",
    "updateDate": "01/24/2018  1:54PM",
    "comments": null,
    "referralNumber": null,
    "chiefComplaint": null,
    "claimId": null,
    "type": "Health Screen",
    "cancelComment": "this is a cancel comment",
    "walkIn": null,
    "serviceLocationName": "St Vincents Hospital",
    "referringName": null
  },
  {
    "appointmentId": 71755,
    "patientId": 311322,
    "startDate": "05/23/2018  5:00PM",
    "endDate": "05/23/2018  5:15PM",
    "resourceName": "test",
    "description": "account, test",
    "status": "Scheduled",
    "insertUserId": "!austin",
    "insertDate": "05/23/2018  3:37PM",
    "updateUserId": "!austin",
    "updateDate": "05/23/2018  3:37PM",
    "comments": null,
    "referralNumber": null,
    "chiefComplaint": null,
    "claimId": null,
    "type": "15 Min Slot",
    "cancelComment": null,
    "walkIn": null,
    "serviceLocationName": null,
    "referringName": "Smith MD, RANDALL"
  },
  {
    "appointmentId": 71782,
    "patientId": 311322,
    "startDate": "06/12/2018 12:00PM",
    "endDate": "06/12/2018 12:10PM",
    "resourceName": "Provider - Scheduling, Test",
    "description": "account, test",
    "status": "Scheduled",
    "insertUserId": "!austin",
    "insertDate": "06/11/2018 11:21AM",
    "updateUserId": "!austin",
    "updateDate": "06/11/2018 11:21AM",
    "comments": null,
    "referralNumber": null,
    "chiefComplaint": null,
    "claimId": null,
    "type": "10 Min Slots",
    "cancelComment": null,
    "walkIn": null,
    "serviceLocationName": null,
    "referringName": "Smith MD, RANDALL"
  },
  {
    "appointmentId": 71818,
    "patientId": 311322,
    "startDate": "06/14/2018  3:00PM",
    "endDate": "06/14/2018  3:20PM",
    "resourceName": "Smith MD, Maria N.",
    "description": "account, test",
    "status": "Scheduled",
    "insertUserId": "!austin",
    "insertDate": "06/16/2018  2:55PM",
    "updateUserId": "!austin",
    "updateDate": "06/16/2018  2:55PM",
    "comments": null,
    "referralNumber": null,
    "chiefComplaint": null,
    "claimId": null,
    "type": "Health Screen",
    "cancelComment": null,
    "walkIn": null,
    "serviceLocationName": null,
    "referringName": "Smith MD, RANDALL"
  },
  {
    "appointmentId": 72162,
    "patientId": 311322,
    "startDate": "01/09/2019 10:45AM",
    "endDate": "01/09/2019 11:05AM",
    "resourceName": "Smith MD, Maria N.",
    "description": "account, test",
    "status": "Checked-Out",
    "insertUserId": "cdaoud",
    "insertDate": "01/09/2019  8:52AM",
    "updateUserId": "cdaoud",
    "updateDate": "01/09/2019  8:55AM",
    "comments": null,
    "referralNumber": null,
    "chiefComplaint": null,
    "claimId": 29952,
    "type": "Health Screen",
    "cancelComment": null,
    "walkIn": null,
    "serviceLocationName": "St Vincents Hospital",
    "referringName": "Smith MD, RANDALL"
  },
  {
    "appointmentId": 72188,
    "patientId": 311322,
    "startDate": "02/27/2019 10:30AM",
    "endDate": "02/27/2019 11:00AM",
    "resourceName": "Adkins MD, Stanley",
    "description": "account, test",
    "status": "Scheduled",
    "insertUserId": "!austin",
    "insertDate": "02/27/2019  3:11PM",
    "updateUserId": "!austin",
    "updateDate": "02/27/2019  3:11PM",
    "comments": "test",
    "referralNumber": null,
    "chiefComplaint": null,
    "claimId": null,
    "type": "30 Min Slot",
    "cancelComment": null,
    "walkIn": null,
    "serviceLocationName": "Miami Lakes Medical Center",
    "referringName": "Smith MD, RANDALL"
  },
  {
    "appointmentId": 72192,
    "patientId": 311322,
    "startDate": "03/06/2019  1:30PM",
    "endDate": "03/06/2019  2:00PM",
    "resourceName": "Buckman MD, Brigid",
    "description": "account, test",
    "status": "Scheduled",
    "insertUserId": "cdaoud",
    "insertDate": "03/06/2019  4:25PM",
    "updateUserId": "cdaoud",
    "updateDate": "03/06/2019  4:25PM",
    "comments": null,
    "referralNumber": null,
    "chiefComplaint": null,
    "claimId": null,
    "type": "New Patient - 30 minutes",
    "cancelComment": null,
    "walkIn": null,
    "serviceLocationName": "St Vincents Hospital",
    "referringName": "Smith MD, RANDALL"
  },
  {
    "appointmentId": 72193,
    "patientId": 311322,
    "startDate": "03/06/2019 10:30AM",
    "endDate": "03/06/2019 11:00AM",
    "resourceName": "Adkins MD, Stanley",
    "description": "account, test",
    "status": "Scheduled",
    "insertUserId": "!austin",
    "insertDate": "03/06/2019  6:16PM",
    "updateUserId": "!austin",
    "updateDate": "03/06/2019  6:16PM",
    "comments": "test",
    "referralNumber": null,
    "chiefComplaint": null,
    "claimId": null,
    "type": "30 Min Slot",
    "cancelComment": null,
    "walkIn": null,
    "serviceLocationName": "Miami Lakes Medical Center",
    "referringName": "Smith MD, RANDALL"
  },
  {
    "appointmentId": 72195,
    "patientId": 311322,
    "startDate": "03/07/2019  9:00AM",
    "endDate": "03/07/2019  9:30AM",
    "resourceName": "Adkins MD, Stanley",
    "description": "account, test",
    "status": "Scheduled",
    "insertUserId": "cdaoud",
    "insertDate": "03/07/2019  4:07PM",
    "updateUserId": "tdavis",
    "updateDate": "05/27/2019  9:45AM",
    "comments": null,
    "referralNumber": null,
    "chiefComplaint": null,
    "claimId": null,
    "type": "5 Min Slot",
    "cancelComment": null,
    "walkIn": null,
    "serviceLocationName": "St Vincents Hospital",
    "referringName": "Smith MD, RANDALL"
  },
  {
    "appointmentId": 72197,
    "patientId": 311322,
    "startDate": "03/20/2019  5:00PM",
    "endDate": "03/20/2019  5:30PM",
    "resourceName": "Aitken MD, Eric M.",
    "description": "account, test",
    "status": "Scheduled",
    "insertUserId": "cdaoud",
    "insertDate": "03/20/2019  8:48AM",
    "updateUserId": "cdaoud",
    "updateDate": "03/20/2019  8:48AM",
    "comments": null,
    "referralNumber": null,
    "chiefComplaint": null,
    "claimId": null,
    "type": "5 Min Slot",
    "cancelComment": null,
    "walkIn": null,
    "serviceLocationName": "St Vincents Hospital",
    "referringName": "Smith MD, RANDALL"
  },
  {
    "appointmentId": 72270,
    "patientId": 311322,
    "startDate": "05/31/2019 11:20AM",
    "endDate": "05/31/2019 11:35AM",
    "resourceName": "Rothfeld MD, Glenn",
    "description": "account, test",
    "status": "Scheduled",
    "insertUserId": "chrisn",
    "insertDate": "05/31/2019 11:22AM",
    "updateUserId": "chrisn",
    "updateDate": "05/31/2019 11:22AM",
    "comments": "",
    "referralNumber": "",
    "chiefComplaint": "",
    "claimId": null,
    "type": "10 Min Slots",
    "cancelComment": null,
    "walkIn": null,
    "serviceLocationName": "Adkins Medical Group",
    "referringName": "Smith MD, RANDALL"
  },
  {
    "appointmentId": 72276,
    "patientId": 311322,
    "startDate": "06/01/2019  3:25PM",
    "endDate": "06/01/2019  3:40PM",
    "resourceName": "Rothfeld MD, Glenn",
    "description": "account, test",
    "status": "Scheduled",
    "insertUserId": "chrisn",
    "insertDate": "05/31/2019  3:28PM",
    "updateUserId": "chrisn",
    "updateDate": "05/31/2019  3:28PM",
    "comments": "",
    "referralNumber": "",
    "chiefComplaint": "",
    "claimId": null,
    "type": "10 Min Slots",
    "cancelComment": null,
    "walkIn": null,
    "serviceLocationName": "Adkins Medical Group",
    "referringName": "Smith MD, RANDALL"
  },
  {
    "appointmentId": 72582,
    "patientId": 311322,
    "startDate": "08/15/2019  8:00AM",
    "endDate": "08/15/2019  8:30AM",
    "resourceName": "Adkins MD, Stanley",
    "description": "account, test",
    "status": "Scheduled",
    "insertUserId": "!austin",
    "insertDate": "08/15/2019  9:31AM",
    "updateUserId": "!austin",
    "updateDate": "08/15/2019  9:31AM",
    "comments": "test",
    "referralNumber": null,
    "chiefComplaint": null,
    "claimId": null,
    "type": "30 Min Slot",
    "cancelComment": null,
    "walkIn": null,
    "serviceLocationName": "Adkins Medical Group",
    "referringName": "Smith MD, RANDALL"
  },
  {
    "appointmentId": 72583,
    "patientId": 311322,
    "startDate": "08/15/2019  8:30AM",
    "endDate": "08/15/2019  9:00AM",
    "resourceName": "Adkins MD, Stanley",
    "description": "account, test",
    "status": "Scheduled",
    "insertUserId": "!austin",
    "insertDate": "08/15/2019  9:32AM",
    "updateUserId": "!austin",
    "updateDate": "08/15/2019  9:32AM",
    "comments": "test",
    "referralNumber": null,
    "chiefComplaint": null,
    "claimId": null,
    "type": "30 Min Slot",
    "cancelComment": null,
    "walkIn": null,
    "serviceLocationName": "Adkins Medical Group",
    "referringName": "Smith MD, RANDALL"
  },
  {
    "appointmentId": 72584,
    "patientId": 311322,
    "startDate": "08/15/2019  9:00AM",
    "endDate": "08/15/2019  9:30AM",
    "resourceName": "Adkins MD, Stanley",
    "description": "account, test",
    "status": "Scheduled",
    "insertUserId": "!austin",
    "insertDate": "08/15/2019  9:32AM",
    "updateUserId": "!austin",
    "updateDate": "08/15/2019  9:32AM",
    "comments": "test",
    "referralNumber": null,
    "chiefComplaint": null,
    "claimId": null,
    "type": "30 Min Slot",
    "cancelComment": null,
    "walkIn": null,
    "serviceLocationName": "Adkins Medical Group",
    "referringName": "Smith MD, RANDALL"
  },
  {
    "appointmentId": 72585,
    "patientId": 311322,
    "startDate": "08/15/2019  9:30AM",
    "endDate": "08/15/2019 10:00AM",
    "resourceName": "Adkins MD, Stanley",
    "description": "account, test",
    "status": "Scheduled",
    "insertUserId": "!austin",
    "insertDate": "08/15/2019  9:32AM",
    "updateUserId": "!austin",
    "updateDate": "08/15/2019  9:32AM",
    "comments": "test",
    "referralNumber": null,
    "chiefComplaint": null,
    "claimId": null,
    "type": "30 Min Slot",
    "cancelComment": null,
    "walkIn": null,
    "serviceLocationName": "Adkins Medical Group",
    "referringName": "Smith MD, RANDALL"
  },
  {
    "appointmentId": 72586,
    "patientId": 311322,
    "startDate": "08/15/2019 10:00AM",
    "endDate": "08/15/2019 10:30AM",
    "resourceName": "Adkins MD, Stanley",
    "description": "account, test",
    "status": "Scheduled",
    "insertUserId": "!austin",
    "insertDate": "08/15/2019  9:32AM",
    "updateUserId": "!austin",
    "updateDate": "08/15/2019  9:32AM",
    "comments": "test",
    "referralNumber": null,
    "chiefComplaint": null,
    "claimId": null,
    "type": "30 Min Slot",
    "cancelComment": null,
    "walkIn": null,
    "serviceLocationName": "Adkins Medical Group",
    "referringName": "Smith MD, RANDALL"
  },
  {
    "appointmentId": 72587,
    "patientId": 311322,
    "startDate": "08/15/2019 10:30AM",
    "endDate": "08/15/2019 11:00AM",
    "resourceName": "Adkins MD, Stanley",
    "description": "account, test",
    "status": "Scheduled",
    "insertUserId": "!austin",
    "insertDate": "08/15/2019  9:32AM",
    "updateUserId": "!austin",
    "updateDate": "08/15/2019  9:32AM",
    "comments": "test",
    "referralNumber": null,
    "chiefComplaint": null,
    "claimId": null,
    "type": "30 Min Slot",
    "cancelComment": null,
    "walkIn": null,
    "serviceLocationName": "Adkins Medical Group",
    "referringName": "Smith MD, RANDALL"
  },
  {
    "appointmentId": 72588,
    "patientId": 311322,
    "startDate": "08/15/2019 11:00AM",
    "endDate": "08/15/2019 11:30AM",
    "resourceName": "Adkins MD, Stanley",
    "description": "account, test",
    "status": "Scheduled",
    "insertUserId": "!austin",
    "insertDate": "08/15/2019  9:32AM",
    "updateUserId": "!austin",
    "updateDate": "08/15/2019  9:32AM",
    "comments": "test",
    "referralNumber": null,
    "chiefComplaint": null,
    "claimId": null,
    "type": "30 Min Slot",
    "cancelComment": null,
    "walkIn": null,
    "serviceLocationName": "Adkins Medical Group",
    "referringName": "Smith MD, RANDALL"
  },
  {
    "appointmentId": 72589,
    "patientId": 311322,
    "startDate": "08/15/2019 11:30AM",
    "endDate": "08/15/2019 12:00PM",
    "resourceName": "Adkins MD, Stanley",
    "description": "account, test",
    "status": "Scheduled",
    "insertUserId": "!austin",
    "insertDate": "08/15/2019  9:32AM",
    "updateUserId": "!austin",
    "updateDate": "08/15/2019  9:32AM",
    "comments": "test",
    "referralNumber": null,
    "chiefComplaint": null,
    "claimId": null,
    "type": "30 Min Slot",
    "cancelComment": null,
    "walkIn": null,
    "serviceLocationName": "Adkins Medical Group",
    "referringName": "Smith MD, RANDALL"
  },
  {
    "appointmentId": 72590,
    "patientId": 311322,
    "startDate": "08/15/2019 12:00PM",
    "endDate": "08/15/2019 12:30PM",
    "resourceName": "Adkins MD, Stanley",
    "description": "account, test",
    "status": "Scheduled",
    "insertUserId": "!austin",
    "insertDate": "08/15/2019  9:32AM",
    "updateUserId": "!austin",
    "updateDate": "08/15/2019  9:32AM",
    "comments": "test",
    "referralNumber": null,
    "chiefComplaint": null,
    "claimId": null,
    "type": "30 Min Slot",
    "cancelComment": null,
    "walkIn": null,
    "serviceLocationName": "Adkins Medical Group",
    "referringName": "Smith MD, RANDALL"
  },
  {
    "appointmentId": 72591,
    "patientId": 311322,
    "startDate": "08/15/2019 12:30PM",
    "endDate": "08/15/2019  1:00PM",
    "resourceName": "Adkins MD, Stanley",
    "description": "account, test",
    "status": "Scheduled",
    "insertUserId": "!austin",
    "insertDate": "08/15/2019  9:32AM",
    "updateUserId": "!austin",
    "updateDate": "08/15/2019  9:32AM",
    "comments": "test",
    "referralNumber": null,
    "chiefComplaint": null,
    "claimId": null,
    "type": "30 Min Slot",
    "cancelComment": null,
    "walkIn": null,
    "serviceLocationName": "Adkins Medical Group",
    "referringName": "Smith MD, RANDALL"
  },
  {
    "appointmentId": 72592,
    "patientId": 311322,
    "startDate": "08/15/2019  1:00PM",
    "endDate": "08/15/2019  1:30PM",
    "resourceName": "Adkins MD, Stanley",
    "description": "account, test",
    "status": "Scheduled",
    "insertUserId": "!austin",
    "insertDate": "08/15/2019  9:32AM",
    "updateUserId": "!austin",
    "updateDate": "08/15/2019  9:32AM",
    "comments": "test",
    "referralNumber": null,
    "chiefComplaint": null,
    "claimId": null,
    "type": "30 Min Slot",
    "cancelComment": null,
    "walkIn": null,
    "serviceLocationName": "Adkins Medical Group",
    "referringName": "Smith MD, RANDALL"
  },
  {
    "appointmentId": 72593,
    "patientId": 311322,
    "startDate": "08/15/2019  1:30PM",
    "endDate": "08/15/2019  2:00PM",
    "resourceName": "Adkins MD, Stanley",
    "description": "account, test",
    "status": "Scheduled",
    "insertUserId": "!austin",
    "insertDate": "08/15/2019  9:32AM",
    "updateUserId": "!austin",
    "updateDate": "08/15/2019  9:32AM",
    "comments": "test",
    "referralNumber": null,
    "chiefComplaint": null,
    "claimId": null,
    "type": "30 Min Slot",
    "cancelComment": null,
    "walkIn": null,
    "serviceLocationName": "Adkins Medical Group",
    "referringName": "Smith MD, RANDALL"
  },
  {
    "appointmentId": 72594,
    "patientId": 311322,
    "startDate": "08/15/2019  2:00PM",
    "endDate": "08/15/2019  2:30PM",
    "resourceName": "Adkins MD, Stanley",
    "description": "account, test",
    "status": "Scheduled",
    "insertUserId": "!austin",
    "insertDate": "08/15/2019  9:32AM",
    "updateUserId": "!austin",
    "updateDate": "08/15/2019  9:32AM",
    "comments": "test",
    "referralNumber": null,
    "chiefComplaint": null,
    "claimId": null,
    "type": "30 Min Slot",
    "cancelComment": null,
    "walkIn": null,
    "serviceLocationName": "Adkins Medical Group",
    "referringName": "Smith MD, RANDALL"
  },
  {
    "appointmentId": 72595,
    "patientId": 311322,
    "startDate": "08/15/2019  2:30PM",
    "endDate": "08/15/2019  3:00PM",
    "resourceName": "Adkins MD, Stanley",
    "description": "account, test",
    "status": "Scheduled",
    "insertUserId": "!austin",
    "insertDate": "08/15/2019  9:32AM",
    "updateUserId": "!austin",
    "updateDate": "08/15/2019  9:32AM",
    "comments": "test",
    "referralNumber": null,
    "chiefComplaint": null,
    "claimId": null,
    "type": "30 Min Slot",
    "cancelComment": null,
    "walkIn": null,
    "serviceLocationName": "Adkins Medical Group",
    "referringName": "Smith MD, RANDALL"
  },
  {
    "appointmentId": 72596,
    "patientId": 311322,
    "startDate": "08/15/2019  3:00PM",
    "endDate": "08/15/2019  3:30PM",
    "resourceName": "Adkins MD, Stanley",
    "description": "account, test",
    "status": "Scheduled",
    "insertUserId": "!austin",
    "insertDate": "08/15/2019  9:32AM",
    "updateUserId": "!austin",
    "updateDate": "08/15/2019  9:32AM",
    "comments": "test",
    "referralNumber": null,
    "chiefComplaint": null,
    "claimId": null,
    "type": "30 Min Slot",
    "cancelComment": null,
    "walkIn": null,
    "serviceLocationName": "Adkins Medical Group",
    "referringName": "Smith MD, RANDALL"
  },
  {
    "appointmentId": 72597,
    "patientId": 311322,
    "startDate": "08/15/2019  3:30PM",
    "endDate": "08/15/2019  4:00PM",
    "resourceName": "Adkins MD, Stanley",
    "description": "account, test",
    "status": "Scheduled",
    "insertUserId": "!austin",
    "insertDate": "08/15/2019  9:32AM",
    "updateUserId": "!austin",
    "updateDate": "08/15/2019  9:32AM",
    "comments": "test",
    "referralNumber": null,
    "chiefComplaint": null,
    "claimId": null,
    "type": "30 Min Slot",
    "cancelComment": null,
    "walkIn": null,
    "serviceLocationName": "Adkins Medical Group",
    "referringName": "Smith MD, RANDALL"
  },
  {
    "appointmentId": 72598,
    "patientId": 311322,
    "startDate": "08/15/2019  4:00PM",
    "endDate": "08/15/2019  4:30PM",
    "resourceName": "Adkins MD, Stanley",
    "description": "account, test",
    "status": "Scheduled",
    "insertUserId": "!austin",
    "insertDate": "08/15/2019  9:33AM",
    "updateUserId": "!austin",
    "updateDate": "08/15/2019  9:33AM",
    "comments": "test",
    "referralNumber": null,
    "chiefComplaint": null,
    "claimId": null,
    "type": "30 Min Slot",
    "cancelComment": null,
    "walkIn": null,
    "serviceLocationName": "Adkins Medical Group",
    "referringName": "Smith MD, RANDALL"
  },
  {
    "appointmentId": 72599,
    "patientId": 311322,
    "startDate": "08/15/2019  4:30PM",
    "endDate": "08/15/2019  5:00PM",
    "resourceName": "Adkins MD, Stanley",
    "description": "account, test",
    "status": "Scheduled",
    "insertUserId": "!austin",
    "insertDate": "08/15/2019  9:33AM",
    "updateUserId": "!austin",
    "updateDate": "08/15/2019  9:33AM",
    "comments": "test",
    "referralNumber": null,
    "chiefComplaint": null,
    "claimId": null,
    "type": "30 Min Slot",
    "cancelComment": null,
    "walkIn": null,
    "serviceLocationName": "Adkins Medical Group",
    "referringName": "Smith MD, RANDALL"
  },
  {
    "appointmentId": 72600,
    "patientId": 311322,
    "startDate": "08/15/2019  5:00PM",
    "endDate": "08/15/2019  5:30PM",
    "resourceName": "Adkins MD, Stanley",
    "description": "account, test",
    "status": "Scheduled",
    "insertUserId": "!austin",
    "insertDate": "08/15/2019  9:33AM",
    "updateUserId": "!austin",
    "updateDate": "08/15/2019  9:33AM",
    "comments": "test",
    "referralNumber": null,
    "chiefComplaint": null,
    "claimId": null,
    "type": "30 Min Slot",
    "cancelComment": null,
    "walkIn": null,
    "serviceLocationName": "Adkins Medical Group",
    "referringName": "Smith MD, RANDALL"
  },
  {
    "appointmentId": 72601,
    "patientId": 311322,
    "startDate": "08/15/2019  5:30PM",
    "endDate": "08/15/2019  6:00PM",
    "resourceName": "Adkins MD, Stanley",
    "description": "account, test",
    "status": "Scheduled",
    "insertUserId": "!austin",
    "insertDate": "08/15/2019  9:33AM",
    "updateUserId": "!austin",
    "updateDate": "08/15/2019  9:33AM",
    "comments": "test",
    "referralNumber": null,
    "chiefComplaint": null,
    "claimId": null,
    "type": "30 Min Slot",
    "cancelComment": null,
    "walkIn": null,
    "serviceLocationName": "Adkins Medical Group",
    "referringName": "Smith MD, RANDALL"
  },
  {
    "appointmentId": 72605,
    "patientId": 311322,
    "startDate": "08/15/2019  7:00AM",
    "endDate": "08/15/2019  7:30AM",
    "resourceName": "Adkins MD, Stanley",
    "description": "account, test",
    "status": "Scheduled",
    "insertUserId": "!austin",
    "insertDate": "08/19/2019  9:05AM",
    "updateUserId": "!austin",
    "updateDate": "08/19/2019  9:05AM",
    "comments": "test",
    "referralNumber": null,
    "chiefComplaint": null,
    "claimId": null,
    "type": "30 Min Slot",
    "cancelComment": null,
    "walkIn": null,
    "serviceLocationName": null,
    "referringName": "Smith MD, RANDALL"
  },
  {
    "appointmentId": 72606,
    "patientId": 311322,
    "startDate": "08/15/2019  7:00AM",
    "endDate": "08/15/2019  7:30AM",
    "resourceName": "Adkins MD, Stanley",
    "description": "account, test",
    "status": "Scheduled",
    "insertUserId": "!austin",
    "insertDate": "08/19/2019  9:05AM",
    "updateUserId": "!austin",
    "updateDate": "08/19/2019  9:05AM",
    "comments": "test",
    "referralNumber": null,
    "chiefComplaint": null,
    "claimId": null,
    "type": "30 Min Slot",
    "cancelComment": null,
    "walkIn": null,
    "serviceLocationName": null,
    "referringName": "Smith MD, RANDALL"
  },
  {
    "appointmentId": 72607,
    "patientId": 311322,
    "startDate": "08/15/2019  7:00AM",
    "endDate": "08/15/2019  7:30AM",
    "resourceName": "Adkins MD, Stanley",
    "description": "account, test",
    "status": "Scheduled",
    "insertUserId": "!austin",
    "insertDate": "08/19/2019  9:05AM",
    "updateUserId": "!austin",
    "updateDate": "08/19/2019  9:05AM",
    "comments": "test",
    "referralNumber": null,
    "chiefComplaint": null,
    "claimId": null,
    "type": "30 Min Slot",
    "cancelComment": null,
    "walkIn": null,
    "serviceLocationName": null,
    "referringName": "Smith MD, RANDALL"
  },
  {
    "appointmentId": 72608,
    "patientId": 311322,
    "startDate": "08/15/2019  7:30AM",
    "endDate": "08/15/2019  8:00AM",
    "resourceName": "Adkins MD, Stanley",
    "description": "account, test",
    "status": "Scheduled",
    "insertUserId": "!austin",
    "insertDate": "08/19/2019  9:05AM",
    "updateUserId": "!austin",
    "updateDate": "08/19/2019  9:05AM",
    "comments": "test",
    "referralNumber": null,
    "chiefComplaint": null,
    "claimId": null,
    "type": "30 Min Slot",
    "cancelComment": null,
    "walkIn": null,
    "serviceLocationName": null,
    "referringName": "Smith MD, RANDALL"
  },
  {
    "appointmentId": 72609,
    "patientId": 311322,
    "startDate": "08/15/2019  7:30AM",
    "endDate": "08/15/2019  8:00AM",
    "resourceName": "Adkins MD, Stanley",
    "description": "account, test",
    "status": "Scheduled",
    "insertUserId": "!austin",
    "insertDate": "08/19/2019  9:05AM",
    "updateUserId": "!austin",
    "updateDate": "08/19/2019  9:05AM",
    "comments": "test",
    "referralNumber": null,
    "chiefComplaint": null,
    "claimId": null,
    "type": "30 Min Slot",
    "cancelComment": null,
    "walkIn": null,
    "serviceLocationName": null,
    "referringName": "Smith MD, RANDALL"
  },
  {
    "appointmentId": 72610,
    "patientId": 311322,
    "startDate": "08/15/2019  7:30AM",
    "endDate": "08/15/2019  8:00AM",
    "resourceName": "Adkins MD, Stanley",
    "description": "account, test",
    "status": "Scheduled",
    "insertUserId": "!austin",
    "insertDate": "08/19/2019  9:05AM",
    "updateUserId": "!austin",
    "updateDate": "08/19/2019  9:05AM",
    "comments": "test",
    "referralNumber": null,
    "chiefComplaint": null,
    "claimId": null,
    "type": "30 Min Slot",
    "cancelComment": null,
    "walkIn": null,
    "serviceLocationName": null,
    "referringName": "Smith MD, RANDALL"
  },
  {
    "appointmentId": 72611,
    "patientId": 311322,
    "startDate": "08/15/2019  7:00AM",
    "endDate": "08/15/2019  7:30AM",
    "resourceName": "Adkins MD, Stanley",
    "description": "account, test",
    "status": "Scheduled",
    "insertUserId": "!austin",
    "insertDate": "08/19/2019  9:06AM",
    "updateUserId": "!austin",
    "updateDate": "08/19/2019  9:06AM",
    "comments": "test",
    "referralNumber": null,
    "chiefComplaint": null,
    "claimId": null,
    "type": "30 Min Slot",
    "cancelComment": null,
    "walkIn": null,
    "serviceLocationName": null,
    "referringName": "Smith MD, RANDALL"
  },
  {
    "appointmentId": 72612,
    "patientId": 311322,
    "startDate": "08/15/2019  7:00AM",
    "endDate": "08/15/2019  7:30AM",
    "resourceName": "Adkins MD, Stanley",
    "description": "account, test",
    "status": "Scheduled",
    "insertUserId": "!austin",
    "insertDate": "08/19/2019  9:06AM",
    "updateUserId": "!austin",
    "updateDate": "08/19/2019  9:06AM",
    "comments": "test",
    "referralNumber": null,
    "chiefComplaint": null,
    "claimId": null,
    "type": "30 Min Slot",
    "cancelComment": null,
    "walkIn": null,
    "serviceLocationName": null,
    "referringName": "Smith MD, RANDALL"
  },
  {
    "appointmentId": 72613,
    "patientId": 311322,
    "startDate": "08/15/2019  7:30AM",
    "endDate": "08/15/2019  8:00AM",
    "resourceName": "Adkins MD, Stanley",
    "description": "account, test",
    "status": "Scheduled",
    "insertUserId": "!austin",
    "insertDate": "08/19/2019  9:06AM",
    "updateUserId": "!austin",
    "updateDate": "08/19/2019  9:06AM",
    "comments": "test",
    "referralNumber": null,
    "chiefComplaint": null,
    "claimId": null,
    "type": "30 Min Slot",
    "cancelComment": null,
    "walkIn": null,
    "serviceLocationName": null,
    "referringName": "Smith MD, RANDALL"
  },
  {
    "appointmentId": 72614,
    "patientId": 311322,
    "startDate": "08/15/2019  7:30AM",
    "endDate": "08/15/2019  8:00AM",
    "resourceName": "Adkins MD, Stanley",
    "description": "account, test",
    "status": "Scheduled",
    "insertUserId": "!austin",
    "insertDate": "08/19/2019  9:06AM",
    "updateUserId": "!austin",
    "updateDate": "08/19/2019  9:06AM",
    "comments": "test",
    "referralNumber": null,
    "chiefComplaint": null,
    "claimId": null,
    "type": "30 Min Slot",
    "cancelComment": null,
    "walkIn": null,
    "serviceLocationName": null,
    "referringName": "Smith MD, RANDALL"
  },
  {
    "appointmentId": 72615,
    "patientId": 311322,
    "startDate": "08/15/2019  9:10AM",
    "endDate": "08/15/2019  9:40AM",
    "resourceName": "Adkins MD, Stanley",
    "description": "account, test",
    "status": "Scheduled",
    "insertUserId": "!austin",
    "insertDate": "08/19/2019  9:07AM",
    "updateUserId": "!austin",
    "updateDate": "08/19/2019  9:07AM",
    "comments": "test",
    "referralNumber": null,
    "chiefComplaint": null,
    "claimId": null,
    "type": "30 Min Slot",
    "cancelComment": null,
    "walkIn": null,
    "serviceLocationName": null,
    "referringName": "Smith MD, RANDALL"
  },
  {
    "appointmentId": 72629,
    "patientId": 311322,
    "startDate": "08/28/2019  4:45PM",
    "endDate": "08/28/2019  5:00PM",
    "resourceName": "Rothfeld MD, Glenn",
    "description": "account, test",
    "status": "Scheduled",
    "insertUserId": "chrisn",
    "insertDate": "08/28/2019  2:56PM",
    "updateUserId": "chrisn",
    "updateDate": "08/28/2019  2:56PM",
    "comments": "hello this is a comment",
    "referralNumber": "yes",
    "chiefComplaint": "everything hurts",
    "claimId": 30375,
    "type": "20 Min Slot",
    "cancelComment": null,
    "walkIn": null,
    "serviceLocationName": "Adult and Pediatric Urology Counsil Bluffs",
    "referringName": "Adesso LPC, William"
  },
  {
    "appointmentId": 72638,
    "patientId": 311322,
    "startDate": "09/03/2019 11:00AM",
    "endDate": "09/03/2019 11:30AM",
    "resourceName": "Adkins MD, Stanley",
    "description": "account, test",
    "status": "Scheduled",
    "insertUserId": "!austin",
    "insertDate": "09/03/2019 10:40AM",
    "updateUserId": "!austin",
    "updateDate": "09/03/2019 10:40AM",
    "comments": "test",
    "referralNumber": null,
    "chiefComplaint": "",
    "claimId": null,
    "type": "30 Min Slot",
    "cancelComment": null,
    "walkIn": null,
    "serviceLocationName": "iSALUS Healthcare",
    "referringName": "Smith MD, RANDALL"
  },
  {
    "appointmentId": 72639,
    "patientId": 311322,
    "startDate": "09/03/2019 11:30AM",
    "endDate": "09/03/2019 12:00PM",
    "resourceName": "Adkins MD, Stanley",
    "description": "account, test",
    "status": "Scheduled",
    "insertUserId": "!austin",
    "insertDate": "09/03/2019 10:41AM",
    "updateUserId": "!austin",
    "updateDate": "09/03/2019 10:41AM",
    "comments": "test",
    "referralNumber": null,
    "chiefComplaint": "",
    "claimId": null,
    "type": "30 Min Slot",
    "cancelComment": null,
    "walkIn": null,
    "serviceLocationName": "iSALUS Healthcare",
    "referringName": "Smith MD, RANDALL"
  },
  {
    "appointmentId": 72640,
    "patientId": 311322,
    "startDate": "09/03/2019 12:30PM",
    "endDate": "09/03/2019  1:00PM",
    "resourceName": "Adkins MD, Stanley",
    "description": "account, test",
    "status": "Scheduled",
    "insertUserId": "!austin",
    "insertDate": "09/03/2019 10:41AM",
    "updateUserId": "!austin",
    "updateDate": "09/03/2019 10:41AM",
    "comments": "test",
    "referralNumber": null,
    "chiefComplaint": "",
    "claimId": 30396,
    "type": "30 Min Slot",
    "cancelComment": null,
    "walkIn": null,
    "serviceLocationName": "St Vincents Hospital",
    "referringName": "Smith MD, RANDALL"
  },
  {
    "appointmentId": 72641,
    "patientId": 311322,
    "startDate": "09/03/2019  1:00PM",
    "endDate": "09/03/2019  1:30PM",
    "resourceName": "Adkins MD, Stanley",
    "description": "account, test",
    "status": "Scheduled",
    "insertUserId": "!austin",
    "insertDate": "09/03/2019 10:41AM",
    "updateUserId": "!austin",
    "updateDate": "09/03/2019 10:41AM",
    "comments": "test",
    "referralNumber": null,
    "chiefComplaint": "",
    "claimId": 30395,
    "type": "30 Min Slot",
    "cancelComment": null,
    "walkIn": null,
    "serviceLocationName": "St Vincents Hospital",
    "referringName": "Smith MD, RANDALL"
  },
  {
    "appointmentId": 72644,
    "patientId": 311322,
    "startDate": "09/03/2019  2:00PM",
    "endDate": "09/03/2019  2:15PM",
    "resourceName": "Collins MD, Ann C.",
    "description": "account, test",
    "status": "Scheduled",
    "insertUserId": "austin",
    "insertDate": "09/03/2019  1:53PM",
    "updateUserId": "austin",
    "updateDate": "09/03/2019  1:53PM",
    "comments": "",
    "referralNumber": "",
    "chiefComplaint": "",
    "claimId": 30383,
    "type": "10 Min Slots",
    "cancelComment": null,
    "walkIn": null,
    "serviceLocationName": "Adkins Medical Group",
    "referringName": "Smith MD, RANDALL"
  },
  {
    "appointmentId": 72694,
    "patientId": 311322,
    "startDate": "10/15/2019  2:00PM",
    "endDate": "10/15/2019  2:20PM",
    "resourceName": "Smith MD, Maria N.",
    "description": "account, test",
    "status": "Scheduled",
    "insertUserId": "chrisn",
    "insertDate": "10/14/2019  2:38PM",
    "updateUserId": "chrisn",
    "updateDate": "10/15/2019  3:30PM",
    "comments": null,
    "referralNumber": null,
    "chiefComplaint": null,
    "claimId": null,
    "type": "Health Screen",
    "cancelComment": null,
    "walkIn": null,
    "serviceLocationName": "St Vincents Hospital",
    "referringName": "Smith MD, RANDALL"
  },
  {
    "appointmentId": 72698,
    "patientId": 311322,
    "startDate": "10/29/2019  5:00PM",
    "endDate": "10/29/2019  5:20PM",
    "resourceName": "Smith MD, Maria N.",
    "description": "account, test",
    "status": "Scheduled",
    "insertUserId": "chrisn",
    "insertDate": "10/28/2019  4:54PM",
    "updateUserId": "chrisn",
    "updateDate": "10/28/2019  4:55PM",
    "comments": null,
    "referralNumber": null,
    "chiefComplaint": null,
    "claimId": null,
    "type": "Health Screen",
    "cancelComment": null,
    "walkIn": null,
    "serviceLocationName": "St Vincents Hospital",
    "referringName": "Smith MD, RANDALL"
  },
  {
    "appointmentId": 72715,
    "patientId": 311322,
    "startDate": "11/05/2019  1:00PM",
    "endDate": "11/05/2019  1:20PM",
    "resourceName": "Smith MD, Maria N.",
    "description": "account, test",
    "status": "Scheduled",
    "insertUserId": "chrisn",
    "insertDate": "11/05/2019 10:47AM",
    "updateUserId": "chrisn",
    "updateDate": "11/05/2019 10:47AM",
    "comments": null,
    "referralNumber": null,
    "chiefComplaint": null,
    "claimId": null,
    "type": "Health Screen",
    "cancelComment": null,
    "walkIn": null,
    "serviceLocationName": "St Vincents Hospital",
    "referringName": "Smith MD, RANDALL"
  },
  {
    "appointmentId": 72765,
    "patientId": 311322,
    "startDate": "11/20/2019 12:00PM",
    "endDate": "11/20/2019 12:30PM",
    "resourceName": "Adkins MD, Stanley",
    "description": "account, test",
    "status": "Scheduled",
    "insertUserId": "chrisn",
    "insertDate": "11/18/2019 10:24AM",
    "updateUserId": "chrisn",
    "updateDate": "11/18/2019 10:24AM",
    "comments": "test",
    "referralNumber": null,
    "chiefComplaint": null,
    "claimId": null,
    "type": "30 Min Slot",
    "cancelComment": null,
    "walkIn": null,
    "serviceLocationName": "Manorcare At Summer Trace",
    "referringName": "Smith MD, RANDALL"
  },
  {
    "appointmentId": 72811,
    "patientId": 311322,
    "startDate": "12/09/2019  3:45AM",
    "endDate": "12/09/2019  4:00AM",
    "resourceName": "Clinic Outpatient 22",
    "description": "account, test",
    "status": "Scheduled",
    "insertUserId": "!austin",
    "insertDate": "12/09/2019  8:04AM",
    "updateUserId": "!austin",
    "updateDate": "12/09/2019  8:04AM",
    "comments": null,
    "referralNumber": null,
    "chiefComplaint": null,
    "claimId": null,
    "type": "15 Min Slot",
    "cancelComment": null,
    "walkIn": null,
    "serviceLocationName": "Celadon Corporate",
    "referringName": "Smith MD, RANDALL"
  },
  {
    "appointmentId": 72966,
    "patientId": 311322,
    "startDate": "03/23/2020  5:30PM",
    "endDate": "03/23/2020  5:40PM",
    "resourceName": "Clinic Outpatient 22",
    "description": "account, test",
    "status": "Scheduled",
    "insertUserId": "!wcassady",
    "insertDate": "03/23/2020  4:23PM",
    "updateUserId": "!wcassady",
    "updateDate": "03/23/2020  4:23PM",
    "comments": null,
    "referralNumber": null,
    "chiefComplaint": null,
    "claimId": null,
    "type": "QA Chrome80 Intake",
    "cancelComment": null,
    "walkIn": null,
    "serviceLocationName": "AAOE 1",
    "referringName": "Smith MD, RANDALL"
  },
  {
    "appointmentId": 72992,
    "patientId": 311322,
    "startDate": "03/30/2020  4:00PM",
    "endDate": "03/30/2020  5:00PM",
    "resourceName": "Adkins MD, Stanley",
    "description": "account, test",
    "status": "Cancelled",
    "insertUserId": "!cdaoud",
    "insertDate": "03/30/2020  3:40PM",
    "updateUserId": "!cdaoud",
    "updateDate": "03/30/2020  4:26PM",
    "comments": "test",
    "referralNumber": null,
    "chiefComplaint": null,
    "claimId": null,
    "type": "New Patient",
    "cancelComment": "test",
    "walkIn": null,
    "serviceLocationName": "BgCtyChldrnUrgntCar",
    "referringName": "Smith MD, RANDALL"
  },
  {
    "appointmentId": 73001,
    "patientId": 311322,
    "startDate": "04/01/2020  2:30PM",
    "endDate": "04/01/2020  3:00PM",
    "resourceName": "test",
    "description": "account, test",
    "status": "Scheduled",
    "insertUserId": "!wcassady",
    "insertDate": "03/31/2020 12:32PM",
    "updateUserId": "!wcassady",
    "updateDate": "03/31/2020 12:32PM",
    "comments": null,
    "referralNumber": null,
    "chiefComplaint": null,
    "claimId": null,
    "type": "10 Min Slots",
    "cancelComment": null,
    "walkIn": null,
    "serviceLocationName": "Test Location",
    "referringName": "Smith MD, RANDALL"
  },
  {
    "appointmentId": 73025,
    "patientId": 311322,
    "startDate": "04/16/2020  1:00PM",
    "endDate": "04/16/2020  2:15PM",
    "resourceName": "DaVita Dialysis North",
    "description": "account, test",
    "status": "Scheduled",
    "insertUserId": "!austin",
    "insertDate": "04/15/2020  2:27PM",
    "updateUserId": "!austin",
    "updateDate": "04/15/2020  2:27PM",
    "comments": "this is a 10 minute comment",
    "referralNumber": null,
    "chiefComplaint": null,
    "claimId": null,
    "type": "10 Min Slots",
    "cancelComment": null,
    "walkIn": null,
    "serviceLocationName": "Adkins Medical Group",
    "referringName": "Smith MD, RANDALL"
  },
  {
    "appointmentId": 73070,
    "patientId": 311322,
    "startDate": "05/12/2020  2:45PM",
    "endDate": "05/12/2020  3:15PM",
    "resourceName": "Adkins MD, Stanley",
    "description": "account, test",
    "status": "Scheduled",
    "insertUserId": "!cdaoud",
    "insertDate": "05/13/2020  3:22PM",
    "updateUserId": "!cdaoud",
    "updateDate": "05/13/2020  3:22PM",
    "comments": "test",
    "referralNumber": null,
    "chiefComplaint": null,
    "claimId": null,
    "type": "30 Min Slot",
    "cancelComment": null,
    "walkIn": null,
    "serviceLocationName": "AAOE 1",
    "referringName": "Smith MD, RANDALL"
  },
  {
    "appointmentId": 73071,
    "patientId": 311322,
    "startDate": "05/13/2020  2:45PM",
    "endDate": "05/13/2020  2:55PM",
    "resourceName": "Adkins MD, Stanley",
    "description": "account, test",
    "status": "Scheduled",
    "insertUserId": "!cdaoud",
    "insertDate": "05/13/2020  3:22PM",
    "updateUserId": "!cdaoud",
    "updateDate": "05/13/2020  3:23PM",
    "comments": "test",
    "referralNumber": null,
    "chiefComplaint": null,
    "claimId": null,
    "type": "10 Min Slots",
    "cancelComment": null,
    "walkIn": null,
    "serviceLocationName": "AAOE 1",
    "referringName": "Smith MD, RANDALL"
  },
  {
    "appointmentId": 73072,
    "patientId": 311322,
    "startDate": "05/13/2020  3:15PM",
    "endDate": "05/13/2020  3:45PM",
    "resourceName": "Adkins MD, Stanley",
    "description": "account, test",
    "status": "Scheduled",
    "insertUserId": "!cdaoud",
    "insertDate": "05/13/2020  3:24PM",
    "updateUserId": "!cdaoud",
    "updateDate": "05/13/2020  4:22PM",
    "comments": "test",
    "referralNumber": null,
    "chiefComplaint": null,
    "claimId": null,
    "type": "30 Min Slot",
    "cancelComment": null,
    "walkIn": null,
    "serviceLocationName": null,
    "referringName": "Smith MD, RANDALL"
  },
  {
    "appointmentId": 73076,
    "patientId": 311322,
    "startDate": "05/02/2022  3:45AM",
    "endDate": "05/02/2022  4:15AM",
    "resourceName": "Adkins MD, Stanley",
    "description": "account, test",
    "status": "Scheduled",
    "insertUserId": "!cdaoud",
    "insertDate": "05/14/2020  9:50AM",
    "updateUserId": "!cdaoud",
    "updateDate": "05/14/2020  9:50AM",
    "comments": "test",
    "referralNumber": null,
    "chiefComplaint": null,
    "claimId": null,
    "type": "30 Min Slot",
    "cancelComment": null,
    "walkIn": null,
    "serviceLocationName": "AAOE 2",
    "referringName": "Smith MD, RANDALL"
  },
  {
    "appointmentId": 73077,
    "patientId": 311322,
    "startDate": "05/02/2022  1:30AM",
    "endDate": "05/02/2022  2:00AM",
    "resourceName": "Adkins MD, Stanley",
    "description": "account, test",
    "status": "Scheduled",
    "insertUserId": "!cdaoud",
    "insertDate": "05/14/2020  9:50AM",
    "updateUserId": "!cdaoud",
    "updateDate": "05/14/2020  9:50AM",
    "comments": "test",
    "referralNumber": null,
    "chiefComplaint": null,
    "claimId": null,
    "type": "30 Min Slot",
    "cancelComment": null,
    "walkIn": null,
    "serviceLocationName": "Bucher Medical Services - Chicago",
    "referringName": "Smith MD, RANDALL"
  },
  {
    "appointmentId": 73087,
    "patientId": 311322,
    "startDate": "05/19/2020 12:45PM",
    "endDate": "05/19/2020 12:55PM",
    "resourceName": "Cochran MD, Sonal",
    "description": "account, test",
    "status": "Scheduled",
    "insertUserId": "!cdaoud",
    "insertDate": "05/19/2020 11:49AM",
    "updateUserId": "!cdaoud",
    "updateDate": "05/19/2020 11:49AM",
    "comments": "this is a 10 minute comment",
    "referralNumber": null,
    "chiefComplaint": null,
    "claimId": null,
    "type": "10 Min Slots",
    "cancelComment": null,
    "walkIn": null,
    "serviceLocationName": null,
    "referringName": "Smith MD, RANDALL"
  },
  {
    "appointmentId": 73088,
    "patientId": 311322,
    "startDate": "05/11/2020  3:00AM",
    "endDate": "05/11/2020  3:30AM",
    "resourceName": "Adkins MD, Stanley",
    "description": "account, test",
    "status": "Scheduled",
    "insertUserId": "!cdaoud",
    "insertDate": "05/21/2020 10:30AM",
    "updateUserId": "!cdaoud",
    "updateDate": "05/21/2020 10:30AM",
    "comments": "test",
    "referralNumber": null,
    "chiefComplaint": null,
    "claimId": null,
    "type": "30 Min Slot",
    "cancelComment": null,
    "walkIn": null,
    "serviceLocationName": "AH - Grafton",
    "referringName": "Smith MD, RANDALL"
  },
  {
    "appointmentId": 73221,
    "patientId": 311322,
    "startDate": "07/30/2020  6:00PM",
    "endDate": "07/30/2020  8:30PM",
    "resourceName": "Sisselman D.O., Stephen",
    "description": "account, test (TEST)",
    "status": "Scheduled",
    "insertUserId": "brad",
    "insertDate": "07/30/2020 11:05AM",
    "updateUserId": "brad",
    "updateDate": "07/30/2020 11:05AM",
    "comments": null,
    "referralNumber": null,
    "chiefComplaint": null,
    "claimId": null,
    "type": "Assessment",
    "cancelComment": null,
    "walkIn": null,
    "serviceLocationName": "St Vincents Hospital",
    "referringName": "Smith MD, RANDALL"
  },
  {
    "appointmentId": 73222,
    "patientId": 311322,
    "startDate": "08/05/2020  6:00PM",
    "endDate": "08/05/2020  6:30PM",
    "resourceName": "Clinic Outpatient 22",
    "description": "account, test (TEST)",
    "status": "Checked-In",
    "insertUserId": "!austin",
    "insertDate": "08/05/2020  4:34PM",
    "updateUserId": "!austin",
    "updateDate": "08/05/2020  4:40PM",
    "comments": "Physical with a lot more information to see what it looks like",
    "referralNumber": null,
    "chiefComplaint": "<li>Physical Complaint<br><li>test",
    "claimId": null,
    "type": "Adult Physical",
    "cancelComment": null,
    "walkIn": null,
    "serviceLocationName": null,
    "referringName": "Smith MD, RANDALL"
  },
  {
    "appointmentId": 73252,
    "patientId": 311322,
    "startDate": "09/10/2020 11:30AM",
    "endDate": "09/10/2020 11:50AM",
    "resourceName": "Smith MD, Maria N.",
    "description": "account, test (TEST)",
    "status": "Checked-In",
    "insertUserId": "!cdaoud",
    "insertDate": "09/10/2020 11:36AM",
    "updateUserId": "!cdaoud",
    "updateDate": "09/10/2020 11:37AM",
    "comments": null,
    "referralNumber": null,
    "chiefComplaint": null,
    "claimId": null,
    "type": "Health Screen",
    "cancelComment": null,
    "walkIn": null,
    "serviceLocationName": null,
    "referringName": "Smith MD, RANDALL"
  },
  {
    "appointmentId": 73253,
    "patientId": 311322,
    "startDate": "09/11/2020 10:00PM",
    "endDate": "09/11/2020 10:30PM",
    "resourceName": "Adkins MD, Stanley",
    "description": "account, test (TEST)",
    "status": "Scheduled",
    "insertUserId": "!cdaoud",
    "insertDate": "09/11/2020  3:52PM",
    "updateUserId": "!cdaoud",
    "updateDate": "09/11/2020  3:52PM",
    "comments": "test",
    "referralNumber": null,
    "chiefComplaint": null,
    "claimId": null,
    "type": "30 Min Slot",
    "cancelComment": null,
    "walkIn": null,
    "serviceLocationName": null,
    "referringName": "Smith MD, RANDALL"
  },
  {
    "appointmentId": 73456,
    "patientId": 311322,
    "startDate": "02/18/2021  2:30PM",
    "endDate": "02/18/2021  2:45PM",
    "resourceName": "Adkins MD, Stanley",
    "description": "Walk-In",
    "status": "Checked-In",
    "insertUserId": "!cdaoud",
    "insertDate": "02/18/2021  2:31PM",
    "updateUserId": "!cdaoud",
    "updateDate": "02/18/2021  2:31PM",
    "comments": null,
    "referralNumber": null,
    "chiefComplaint": "",
    "claimId": 30685,
    "type": null,
    "cancelComment": null,
    "walkIn": "Y",
    "serviceLocationName": "AAOE 1",
    "referringName": "Acanfora DC, Michael"
  },
  {
    "appointmentId": 73557,
    "patientId": 311322,
    "startDate": "04/08/2021 10:25AM",
    "endDate": "04/08/2021 10:40AM",
    "resourceName": "Adkins MD, Stanley",
    "description": "Walk-In",
    "status": "Checked-In",
    "insertUserId": "!cdaoud",
    "insertDate": "04/08/2021 10:28AM",
    "updateUserId": "!cdaoud",
    "updateDate": "04/08/2021 10:28AM",
    "comments": null,
    "referralNumber": null,
    "chiefComplaint": "",
    "claimId": 30711,
    "type": null,
    "cancelComment": null,
    "walkIn": "Y",
    "serviceLocationName": "AAOE 1",
    "referringName": "Acanfora DC, Michael"
  },
  {
    "appointmentId": 73565,
    "patientId": 311322,
    "startDate": "11/11/2019  2:00AM",
    "endDate": "11/11/2019  2:15AM",
    "resourceName": "Neuro Rehab Center Outpatient with a longer name",
    "description": "account, test (TEST)",
    "status": "Scheduled",
    "insertUserId": "!dnorris",
    "insertDate": "04/12/2021  4:58PM",
    "updateUserId": "!dnorris",
    "updateDate": "04/12/2021  4:58PM",
    "comments": null,
    "referralNumber": null,
    "chiefComplaint": null,
    "claimId": null,
    "type": "15 Min Slot",
    "cancelComment": null,
    "walkIn": null,
    "serviceLocationName": null,
    "referringName": "Acanfora DC, Michael"
  },
  {
    "appointmentId": 73598,
    "patientId": 311322,
    "startDate": "06/08/2021 12:00PM",
    "endDate": "06/08/2021 12:30PM",
    "resourceName": "Adkins MD, Stanley",
    "description": "account, test (TEST)",
    "status": "Scheduled",
    "insertUserId": "!binman",
    "insertDate": "06/06/2021 10:53AM",
    "updateUserId": "!binman",
    "updateDate": "06/06/2021 10:53AM",
    "comments": "test",
    "referralNumber": null,
    "chiefComplaint": null,
    "claimId": null,
    "type": "30 Min Slot",
    "cancelComment": null,
    "walkIn": null,
    "serviceLocationName": null,
    "referringName": "Acanfora DC, Michael"
  },
  {
    "appointmentId": 73603,
    "patientId": 311322,
    "startDate": "06/14/2021  9:00AM",
    "endDate": "06/14/2021  9:30AM",
    "resourceName": "Adkins MD, Stanley",
    "description": "account, test (TEST)",
    "status": "Scheduled",
    "insertUserId": "!chandler",
    "insertDate": "06/14/2021  1:44PM",
    "updateUserId": "!chandler",
    "updateDate": "06/14/2021  1:44PM",
    "comments": "test",
    "referralNumber": null,
    "chiefComplaint": null,
    "claimId": null,
    "type": "30 Min Slot",
    "cancelComment": null,
    "walkIn": null,
    "serviceLocationName": "AH - Grafton",
    "referringName": "Acanfora DC, Michael"
  },
  {
    "appointmentId": 73634,
    "patientId": 311322,
    "startDate": "08/10/2021 10:00AM",
    "endDate": "08/10/2021 10:05AM",
    "resourceName": "Aitken MD, Eric M.",
    "description": "account, test (TEST)",
    "status": "Scheduled",
    "insertUserId": "cdaoud",
    "insertDate": "08/10/2021  8:06AM",
    "updateUserId": "cdaoud",
    "updateDate": "08/10/2021  8:06AM",
    "comments": null,
    "referralNumber": null,
    "chiefComplaint": null,
    "claimId": null,
    "type": "5 Min Slot",
    "cancelComment": null,
    "walkIn": null,
    "serviceLocationName": "St Vincents Hospital",
    "referringName": "Acanfora DC, Michael"
  },
  {
    "appointmentId": 73823,
    "patientId": 311322,
    "startDate": "09/08/2021  3:00PM",
    "endDate": "09/08/2021  3:10PM",
    "resourceName": "Adkins MD, Stanley",
    "description": "account, test (TEST)",
    "status": "Scheduled",
    "insertUserId": "!blake",
    "insertDate": "09/07/2021  1:32PM",
    "updateUserId": "!blake",
    "updateDate": "09/07/2021  1:32PM",
    "comments": "this is a 10 minute comment",
    "referralNumber": "",
    "chiefComplaint": "",
    "claimId": null,
    "type": "10 Min Slots",
    "cancelComment": null,
    "walkIn": null,
    "serviceLocationName": "AAOE 2",
    "referringName": "Acanfora DC, Michael"
  },
  {
    "appointmentId": 73835,
    "patientId": 311322,
    "startDate": "09/13/2021 12:00PM",
    "endDate": "09/13/2021 12:30PM",
    "resourceName": "Brooks MD, Kristi F.",
    "description": "account, test (TEST)",
    "status": "Scheduled",
    "insertUserId": "cdaoud",
    "insertDate": "09/13/2021 10:24AM",
    "updateUserId": "cdaoud",
    "updateDate": "09/13/2021 10:24AM",
    "comments": "Physical with a lot more information to see what it looks like",
    "referralNumber": null,
    "chiefComplaint": "<li>Physical Complaint<br><li>test",
    "claimId": null,
    "type": "Adult Physical",
    "cancelComment": null,
    "walkIn": null,
    "serviceLocationName": "St Vincents Hospital",
    "referringName": "Acanfora DC, Michael"
  },
  {
    "appointmentId": 73836,
    "patientId": 311322,
    "startDate": "09/15/2021  2:00PM",
    "endDate": "09/15/2021  2:30PM",
    "resourceName": "Brooks MD, Kristi F.",
    "description": "account, test (TEST)",
    "status": "Scheduled",
    "insertUserId": "brad",
    "insertDate": "09/15/2021  8:24AM",
    "updateUserId": "brad",
    "updateDate": "09/15/2021  8:24AM",
    "comments": "Physical with a lot more information to see what it looks like",
    "referralNumber": null,
    "chiefComplaint": "<li>Physical Complaint<br><li>test",
    "claimId": null,
    "type": "Adult Physical",
    "cancelComment": null,
    "walkIn": null,
    "serviceLocationName": "St Vincents Hospital",
    "referringName": "Acanfora DC, Michael"
  },
  {
    "appointmentId": 73912,
    "patientId": 311322,
    "startDate": "11/08/2021 12:30PM",
    "endDate": "11/08/2021  1:00PM",
    "resourceName": "Brooks MD, Kristi F.",
    "description": "account, test (TEST)",
    "status": "Scheduled",
    "insertUserId": "cdaoud",
    "insertDate": "11/09/2021  8:28AM",
    "updateUserId": "cdaoud",
    "updateDate": "11/09/2021  8:28AM",
    "comments": "Physical with a lot more information to see what it looks like",
    "referralNumber": null,
    "chiefComplaint": "<li>Physical Complaint<br><li>test",
    "claimId": 30726,
    "type": "Adult Physical",
    "cancelComment": null,
    "walkIn": null,
    "serviceLocationName": "St Vincents Hospital",
    "referringName": "Acanfora DC, Michael"
  },
  {
    "appointmentId": 73913,
    "patientId": 311322,
    "startDate": "11/09/2021  3:00PM",
    "endDate": "11/09/2021  3:30PM",
    "resourceName": "Brooks MD, Kristi F.",
    "description": "account, test (TEST)",
    "status": "Scheduled",
    "insertUserId": "brad",
    "insertDate": "11/09/2021 10:19AM",
    "updateUserId": "brad",
    "updateDate": "11/09/2021 10:19AM",
    "comments": "Physical with a lot more information to see what it looks like",
    "referralNumber": null,
    "chiefComplaint": "<li>Physical Complaint<br><li>test",
    "claimId": null,
    "type": "Adult Physical",
    "cancelComment": null,
    "walkIn": null,
    "serviceLocationName": "St Vincents Hospital",
    "referringName": "Acanfora DC, Michael"
  },
  {
    "appointmentId": 73919,
    "patientId": 311322,
    "startDate": "11/11/2021 12:00PM",
    "endDate": "11/11/2021 12:30PM",
    "resourceName": "Brooks MD, Kristi F.",
    "description": "account, test (TEST)",
    "status": "Scheduled",
    "insertUserId": "brad",
    "insertDate": "11/11/2021  8:45AM",
    "updateUserId": "brad",
    "updateDate": "11/11/2021  8:45AM",
    "comments": "Physical with a lot more information to see what it looks like",
    "referralNumber": null,
    "chiefComplaint": "<li>Physical Complaint<br><li>test",
    "claimId": null,
    "type": "Adult Physical",
    "cancelComment": null,
    "walkIn": null,
    "serviceLocationName": "St Vincents Hospital",
    "referringName": "Acanfora DC, Michael"
  },
  {
    "appointmentId": 73936,
    "patientId": 311322,
    "startDate": "12/01/2021  5:00PM",
    "endDate": "12/01/2021  5:20PM",
    "resourceName": "Smith MD, Maria N.",
    "description": "account, test (TEST)",
    "status": "Scheduled",
    "insertUserId": "!cdaoud",
    "insertDate": "12/01/2021  2:56PM",
    "updateUserId": "!cdaoud",
    "updateDate": "12/01/2021  2:56PM",
    "comments": null,
    "referralNumber": null,
    "chiefComplaint": null,
    "claimId": 30753,
    "type": "Health Screen",
    "cancelComment": null,
    "walkIn": null,
    "serviceLocationName": "AAOE 1",
    "referringName": "Acanfora DC, Michael"
  },
  {
    "appointmentId": 73942,
    "patientId": 311322,
    "startDate": "12/13/2021  5:30PM",
    "endDate": "12/13/2021  6:00PM",
    "resourceName": "Brooks MD, Kristi F.",
    "description": "account, test (TEST)",
    "status": "Scheduled",
    "insertUserId": "mlong",
    "insertDate": "12/13/2021  4:48PM",
    "updateUserId": "mlong",
    "updateDate": "12/13/2021  4:48PM",
    "comments": "Physical with a lot more information to see what it looks like",
    "referralNumber": null,
    "chiefComplaint": "<li>Physical Complaint<br><li>test",
    "claimId": 30754,
    "type": "Adult Physical",
    "cancelComment": null,
    "walkIn": null,
    "serviceLocationName": null,
    "referringName": "Acanfora DC, Michael"
  },
  {
    "appointmentId": 73943,
    "patientId": 311322,
    "startDate": "12/14/2021 10:00AM",
    "endDate": "12/14/2021 10:20AM",
    "resourceName": "Smith MD, Maria N.",
    "description": "account, test (TEST)",
    "status": "Scheduled",
    "insertUserId": "!cdaoud",
    "insertDate": "12/14/2021  9:04AM",
    "updateUserId": "!cdaoud",
    "updateDate": "12/14/2021  9:04AM",
    "comments": null,
    "referralNumber": null,
    "chiefComplaint": "test",
    "claimId": 30755,
    "type": "Health Screen",
    "cancelComment": null,
    "walkIn": null,
    "serviceLocationName": "AAOE 1",
    "referringName": "Acanfora DC, Michael"
  },
  {
    "appointmentId": 74209,
    "patientId": 311322,
    "startDate": "05/05/2022  1:00PM",
    "endDate": "05/05/2022  1:30PM",
    "resourceName": "Brooks MD, Kristi F.",
    "description": "account, test (TEST)",
    "status": "Scheduled",
    "insertUserId": "cdaoud",
    "insertDate": "05/05/2022  3:58PM",
    "updateUserId": "cdaoud",
    "updateDate": "05/05/2022  3:58PM",
    "comments": "Physical with a lot more information to see what it looks like",
    "referralNumber": null,
    "chiefComplaint": "<li>Physical Complaint<br><li>test",
    "claimId": null,
    "type": "Adult Physical",
    "cancelComment": null,
    "walkIn": null,
    "serviceLocationName": "St Vincents Hospital",
    "referringName": "Acanfora DC, Michael"
  },
  {
    "appointmentId": 74565,
    "patientId": 311322,
    "startDate": "07/11/2022  2:00PM",
    "endDate": "07/11/2022  2:20PM",
    "resourceName": "Smith MD, Maria N.",
    "description": "account, test (TEST)",
    "status": "Scheduled",
    "insertUserId": "!cdaoud",
    "insertDate": "07/11/2022  1:03PM",
    "updateUserId": "!cdaoud",
    "updateDate": "07/11/2022  1:03PM",
    "comments": null,
    "referralNumber": null,
    "chiefComplaint": null,
    "claimId": null,
    "type": "Health Screen",
    "cancelComment": null,
    "walkIn": null,
    "serviceLocationName": "AAOE 1",
    "referringName": "Acanfora DC, Michael"
  },
  {
    "appointmentId": 74627,
    "patientId": 311322,
    "startDate": "08/19/2022  1:00PM",
    "endDate": "08/19/2022  1:20PM",
    "resourceName": "Smith MD, Maria N.",
    "description": "account, test (TEST)",
    "status": "Checked-In",
    "insertUserId": "!cdaoud",
    "insertDate": "08/19/2022 11:08AM",
    "updateUserId": "!cdaoud",
    "updateDate": "08/19/2022 11:09AM",
    "comments": null,
    "referralNumber": null,
    "chiefComplaint": null,
    "claimId": 30977,
    "type": "20 Min Slot",
    "cancelComment": null,
    "walkIn": null,
    "serviceLocationName": "AAOE 1 X",
    "referringName": "Acanfora DC, Michael"
  },
  {
    "appointmentId": 74635,
    "patientId": 311322,
    "startDate": "08/23/2022 11:00AM",
    "endDate": "08/23/2022 11:30AM",
    "resourceName": "Adkins MD, Stanley",
    "description": "account, test (TEST)",
    "status": "Checked-Out",
    "insertUserId": "!dstarnes",
    "insertDate": "08/22/2022  8:06AM",
    "updateUserId": "!michell",
    "updateDate": "08/22/2022  9:48AM",
    "comments": "test",
    "referralNumber": null,
    "chiefComplaint": null,
    "claimId": 30980,
    "type": "30 Min Slot",
    "cancelComment": null,
    "walkIn": null,
    "serviceLocationName": null,
    "referringName": "Acanfora DC, Michael"
  },
  {
    "appointmentId": 74640,
    "patientId": 311322,
    "startDate": "08/22/2022 12:30PM",
    "endDate": "08/22/2022 12:50PM",
    "resourceName": "Smith MD, Maria N.",
    "description": "account, test (TEST)",
    "status": "Scheduled",
    "insertUserId": "!cdaoud",
    "insertDate": "08/22/2022 10:40AM",
    "updateUserId": "!cdaoud",
    "updateDate": "08/22/2022 10:40AM",
    "comments": null,
    "referralNumber": null,
    "chiefComplaint": null,
    "claimId": null,
    "type": "Health Screen",
    "cancelComment": null,
    "walkIn": null,
    "serviceLocationName": "AAOE 1",
    "referringName": "Acanfora DC, Michael"
  },
  {
    "appointmentId": 74670,
    "patientId": 311322,
    "startDate": "09/01/2022  5:30PM",
    "endDate": "09/01/2022  5:50PM",
    "resourceName": "Smith MD, Maria N.",
    "description": "account, test (TEST)",
    "status": "Scheduled",
    "insertUserId": "!cdaoud",
    "insertDate": "09/01/2022  2:40PM",
    "updateUserId": "!cdaoud",
    "updateDate": "09/01/2022  2:40PM",
    "comments": null,
    "referralNumber": null,
    "chiefComplaint": null,
    "claimId": null,
    "type": "Health Screen",
    "cancelComment": null,
    "walkIn": null,
    "serviceLocationName": "AAOE 1",
    "referringName": "Acanfora DC, Michael"
  },
  {
    "appointmentId": 74683,
    "patientId": 311322,
    "startDate": "09/16/2022  2:00PM",
    "endDate": "09/16/2022  2:30PM",
    "resourceName": "Adkins MD, Stanley",
    "description": "account, test (TEST)",
    "status": "Scheduled",
    "insertUserId": "!michell",
    "insertDate": "09/12/2022  1:19PM",
    "updateUserId": "!michell",
    "updateDate": "09/12/2022  1:19PM",
    "comments": "test",
    "referralNumber": null,
    "chiefComplaint": null,
    "claimId": 31054,
    "type": "30 Min Slot",
    "cancelComment": null,
    "walkIn": null,
    "serviceLocationName": "Adult and Pediatric Urology Counsil Bluffs",
    "referringName": "Acanfora DC, Michael"
  },
  {
    "appointmentId": 75737,
    "patientId": 311322,
    "startDate": "10/10/2022 11:00AM",
    "endDate": "10/10/2022 11:30AM",
    "resourceName": "Brooks MD, Kristi F.",
    "description": "account, test (TEST)",
    "status": "Scheduled",
    "insertUserId": "!gferrer",
    "insertDate": "10/10/2022 11:06AM",
    "updateUserId": "!gferrer",
    "updateDate": "10/10/2022 11:06AM",
    "comments": "Physical with a lot more information to see what it looks like",
    "referralNumber": null,
    "chiefComplaint": "<li>Physical Complaint<br><li>test",
    "claimId": null,
    "type": "Adult Physical",
    "cancelComment": null,
    "walkIn": null,
    "serviceLocationName": null,
    "referringName": "Acanfora DC, Michael"
  },
  {
    "appointmentId": 75738,
    "patientId": 311322,
    "startDate": "10/10/2022  3:30PM",
    "endDate": "10/10/2022  4:00PM",
    "resourceName": "Brooks MD, Kristi F.",
    "description": "account, test (TEST)",
    "status": "Checked-Out",
    "insertUserId": "!gferrer",
    "insertDate": "10/10/2022 12:10PM",
    "updateUserId": "!gferrer",
    "updateDate": "10/10/2022 12:11PM",
    "comments": "Physical with a lot more information to see what it looks like",
    "referralNumber": null,
    "chiefComplaint": "<li>Physical Complaint<br><li>test",
    "claimId": null,
    "type": "Adult Physical",
    "cancelComment": null,
    "walkIn": null,
    "serviceLocationName": null,
    "referringName": "Acanfora DC, Michael"
  },
  {
    "appointmentId": 75919,
    "patientId": 311322,
    "startDate": "01/05/2023 12:30PM",
    "endDate": "01/05/2023 12:40PM",
    "resourceName": "Adkins MD, Stanley",
    "description": "account, test (TEST)",
    "status": "Scheduled",
    "insertUserId": "!kevin",
    "insertDate": "01/05/2023 10:52AM",
    "updateUserId": "!kevin",
    "updateDate": "01/05/2023 10:52AM",
    "comments": "test",
    "referralNumber": null,
    "chiefComplaint": null,
    "claimId": null,
    "type": "10 Min Slots",
    "cancelComment": null,
    "walkIn": null,
    "serviceLocationName": null,
    "referringName": "Acanfora DC, Michael"
  },
  {
    "appointmentId": 75920,
    "patientId": 311322,
    "startDate": "01/06/2023 11:15AM",
    "endDate": "01/06/2023 11:25AM",
    "resourceName": "Adkins MD, Stanley",
    "description": "account, test (TEST)",
    "status": "Scheduled",
    "insertUserId": "!kevin",
    "insertDate": "01/06/2023  9:10AM",
    "updateUserId": "!kevin",
    "updateDate": "01/06/2023  9:10AM",
    "comments": "test",
    "referralNumber": null,
    "chiefComplaint": null,
    "claimId": null,
    "type": "10 Min Slots",
    "cancelComment": null,
    "walkIn": null,
    "serviceLocationName": null,
    "referringName": "Acanfora DC, Michael"
  },
  {
    "appointmentId": 75927,
    "patientId": 311322,
    "startDate": "01/12/2023  3:00PM",
    "endDate": "01/12/2023  3:15PM",
    "resourceName": "Adkins MD, Stanley",
    "description": "account, test (TEST)",
    "status": "Scheduled",
    "insertUserId": "!kevin",
    "insertDate": "01/12/2023 12:45PM",
    "updateUserId": "!kevin",
    "updateDate": "01/12/2023 12:46PM",
    "comments": "test",
    "referralNumber": null,
    "chiefComplaint": null,
    "claimId": null,
    "type": "10 Min Slots",
    "cancelComment": null,
    "walkIn": null,
    "serviceLocationName": null,
    "referringName": "Acanfora DC, Michael"
  },
  {
    "appointmentId": 75969,
    "patientId": 311322,
    "startDate": "02/01/2023  1:00PM",
    "endDate": "02/01/2023  1:20PM",
    "resourceName": "test, onboard",
    "description": "account, test (TEST)",
    "status": "Scheduled",
    "insertUserId": "!gferrer",
    "insertDate": "01/29/2023  2:17PM",
    "updateUserId": "!gferrer",
    "updateDate": "01/29/2023  2:17PM",
    "comments": null,
    "referralNumber": null,
    "chiefComplaint": "FU Appt Audubon Plaza",
    "claimId": null,
    "type": "20 Min Slot",
    "cancelComment": null,
    "walkIn": null,
    "serviceLocationName": "Audubon Plaza",
    "referringName": "Acanfora DC, Michael"
  },
  {
    "appointmentId": 75984,
    "patientId": 311322,
    "startDate": "02/10/2023  5:00PM",
    "endDate": "02/10/2023  5:30PM",
    "resourceName": "Adkins MD, Stanley",
    "description": "account, test (CKCC)",
    "status": "Checked-Out",
    "insertUserId": "!binman",
    "insertDate": "02/09/2023  3:09PM",
    "updateUserId": "!binman",
    "updateDate": "02/10/2023  9:26AM",
    "comments": "test",
    "referralNumber": null,
    "chiefComplaint": null,
    "claimId": 31113,
    "type": "30 Min Slot",
    "cancelComment": null,
    "walkIn": null,
    "serviceLocationName": "AAOE 1",
    "referringName": "Acanfora DC, Michael"
  },
  {
    "appointmentId": 75993,
    "patientId": 311322,
    "startDate": "02/17/2023  2:00PM",
    "endDate": "02/17/2023  2:30PM",
    "resourceName": "Adkins MD, Stanley",
    "description": "account, test (CKCC)",
    "status": "Scheduled",
    "insertUserId": "!binman",
    "insertDate": "02/14/2023 10:21AM",
    "updateUserId": "!binman",
    "updateDate": "02/14/2023 10:21AM",
    "comments": "test",
    "referralNumber": null,
    "chiefComplaint": null,
    "claimId": null,
    "type": "30 Min Slot",
    "cancelComment": null,
    "walkIn": null,
    "serviceLocationName": "Audubon Plaza",
    "referringName": "Acanfora DC, Michael"
  },
  {
    "appointmentId": 75996,
    "patientId": 311322,
    "startDate": "02/14/2023 12:00PM",
    "endDate": "02/14/2023 12:30PM",
    "resourceName": "Adkins MD, Stanley",
    "description": "account, test (CKCC)",
    "status": "Scheduled",
    "insertUserId": "!michell",
    "insertDate": "02/14/2023  1:01PM",
    "updateUserId": "!michell",
    "updateDate": "02/14/2023  1:01PM",
    "comments": "test",
    "referralNumber": null,
    "chiefComplaint": null,
    "claimId": null,
    "type": "30 Min Slot",
    "cancelComment": null,
    "walkIn": null,
    "serviceLocationName": "Andrew Sagarsee",
    "referringName": "Acanfora DC, Michael"
  },
  {
    "appointmentId": 75998,
    "patientId": 311322,
    "startDate": "02/15/2023 12:00PM",
    "endDate": "02/15/2023 12:30PM",
    "resourceName": "Adkins MD, Stanley",
    "description": "account, test (CKCC)",
    "status": "Scheduled",
    "insertUserId": "!michell",
    "insertDate": "02/14/2023  1:04PM",
    "updateUserId": "!michell",
    "updateDate": "02/14/2023  2:00PM",
    "comments": null,
    "referralNumber": null,
    "chiefComplaint": null,
    "claimId": null,
    "type": "30 Min Slot",
    "cancelComment": null,
    "walkIn": null,
    "serviceLocationName": "AAOE 3 test",
    "referringName": "Acanfora DC, Michael"
  },
  {
    "appointmentId": 76025,
    "patientId": 311322,
    "startDate": "03/06/2023  2:00PM",
    "endDate": "03/06/2023  2:30PM",
    "resourceName": "Adkins MD, Stanley",
    "description": "account, test (CKCC)",
    "status": "Scheduled",
    "insertUserId": "!chandler",
    "insertDate": "03/06/2023 11:37AM",
    "updateUserId": "!chandler",
    "updateDate": "03/06/2023 11:38AM",
    "comments": "test",
    "referralNumber": null,
    "chiefComplaint": null,
    "claimId": 31129,
    "type": "30 Min Slot",
    "cancelComment": null,
    "walkIn": null,
    "serviceLocationName": "Adkins Medical Group",
    "referringName": "Acanfora DC, Michael"
  },
  {
    "appointmentId": 76032,
    "patientId": 311322,
    "startDate": "03/10/2023 10:00AM",
    "endDate": "03/10/2023 10:30AM",
    "resourceName": "Adkins MD, Stanley",
    "description": "account, test (CKCC)",
    "status": "Scheduled",
    "insertUserId": "!michell",
    "insertDate": "03/10/2023  1:24AM",
    "updateUserId": "!michell",
    "updateDate": "03/10/2023  1:24AM",
    "comments": "test",
    "referralNumber": null,
    "chiefComplaint": null,
    "claimId": null,
    "type": "30 Min Slot",
    "cancelComment": null,
    "walkIn": null,
    "serviceLocationName": "iSALUS Healthcare",
    "referringName": "Acanfora DC, Michael"
  },
  {
    "appointmentId": 76042,
    "patientId": 311322,
    "startDate": "03/31/2023  1:00PM",
    "endDate": "03/31/2023  2:00PM",
    "resourceName": "Adkins MD, Stanley",
    "description": "account, test (CKCC)",
    "status": "Scheduled",
    "insertUserId": "!gferrer",
    "insertDate": "03/22/2023  2:19PM",
    "updateUserId": "!gferrer",
    "updateDate": "03/22/2023  2:19PM",
    "comments": "test",
    "referralNumber": null,
    "chiefComplaint": "New eval",
    "claimId": null,
    "type": "Consulation - 60 minutes",
    "cancelComment": null,
    "walkIn": null,
    "serviceLocationName": "Jeffersonville Office",
    "referringName": "Acanfora DC, Michael"
  },
  {
    "appointmentId": 76048,
    "patientId": 311322,
    "startDate": "04/05/2023 12:15PM",
    "endDate": "04/05/2023 12:45PM",
    "resourceName": "Adkins MD, Stanley",
    "description": "account, test F. (CKCC)",
    "status": "Scheduled",
    "insertUserId": "!michell",
    "insertDate": "04/05/2023  1:12PM",
    "updateUserId": "!michell",
    "updateDate": "04/05/2023  1:12PM",
    "comments": "test",
    "referralNumber": null,
    "chiefComplaint": null,
    "claimId": null,
    "type": "30 Min Slot",
    "cancelComment": null,
    "walkIn": null,
    "serviceLocationName": "AAOE 1 X",
    "referringName": "Acanfora DC, Michael"
  },
  {
    "appointmentId": 76110,
    "patientId": 311322,
    "startDate": "05/16/2023  3:00PM",
    "endDate": "05/16/2023  3:10PM",
    "resourceName": "Smith M.D., Gregory A.",
    "description": "account, test F. (CKCC)",
    "status": "Checked-Out",
    "insertUserId": "!cdaoud",
    "insertDate": "05/16/2023  2:05PM",
    "updateUserId": "!cdaoud",
    "updateDate": "05/16/2023  2:10PM",
    "comments": "this is a 10 minute comment",
    "referralNumber": null,
    "chiefComplaint": null,
    "claimId": 31147,
    "type": "10 Min Slots",
    "cancelComment": null,
    "walkIn": null,
    "serviceLocationName": null,
    "referringName": "Acanfora DC, Michael"
  },
  {
    "appointmentId": 76127,
    "patientId": 311322,
    "startDate": "06/07/2023  6:15PM",
    "endDate": "06/07/2023  6:25PM",
    "resourceName": "Smith M.D., Gregory A.",
    "description": "account, test F. (CKCC)",
    "status": "Scheduled",
    "insertUserId": "!cdaoud",
    "insertDate": "06/07/2023  4:19PM",
    "updateUserId": "!cdaoud",
    "updateDate": "06/07/2023  4:19PM",
    "comments": "this is a 10 minute comment",
    "referralNumber": null,
    "chiefComplaint": null,
    "claimId": 31151,
    "type": "10 Min Slots",
    "cancelComment": null,
    "walkIn": null,
    "serviceLocationName": "AAOE 4",
    "referringName": "Acanfora DC, Michael"
  },
  {
    "appointmentId": 76173,
    "patientId": 311322,
    "startDate": "06/23/2021  2:00PM",
    "endDate": "06/23/2021  2:20PM",
    "resourceName": "test, onboard",
    "description": "account, test F. (CKCC)",
    "status": "Checked-Out",
    "insertUserId": "!gferrer",
    "insertDate": "06/18/2023 10:55AM",
    "updateUserId": "!gferrer",
    "updateDate": "06/18/2023 11:05AM",
    "comments": null,
    "referralNumber": null,
    "chiefComplaint": "that",
    "claimId": null,
    "type": "20 Min Slot",
    "cancelComment": null,
    "walkIn": null,
    "serviceLocationName": "Audubon Plaza",
    "referringName": "Acanfora DC, Michael"
  },
  {
    "appointmentId": 76176,
    "patientId": 311322,
    "startDate": "06/29/2023 10:00AM",
    "endDate": "06/29/2023 10:30AM",
    "resourceName": "test, onboard",
    "description": "account, test F. (CKCC)",
    "status": "Scheduled",
    "insertUserId": "!gferrer",
    "insertDate": "06/18/2023 11:05AM",
    "updateUserId": "!gferrer",
    "updateDate": "06/18/2023 11:05AM",
    "comments": "test",
    "referralNumber": null,
    "chiefComplaint": "eGFR",
    "claimId": null,
    "type": "30 Min Slot",
    "cancelComment": null,
    "walkIn": null,
    "serviceLocationName": "Audubon Plaza",
    "referringName": "Acanfora DC, Michael"
  },
  {
    "appointmentId": 76178,
    "patientId": 311322,
    "startDate": "06/21/2023 11:00AM",
    "endDate": "06/21/2023 11:30AM",
    "resourceName": "Adkins MD, Stanley",
    "description": "account, test F. (CKCC)",
    "status": "Checked-Out",
    "insertUserId": "!gferrer",
    "insertDate": "06/21/2023  8:51AM",
    "updateUserId": "!gferrer",
    "updateDate": "06/21/2023  9:20AM",
    "comments": "test",
    "referralNumber": null,
    "chiefComplaint": "Follow",
    "claimId": null,
    "type": "30 Min Slot",
    "cancelComment": null,
    "walkIn": null,
    "serviceLocationName": "iSALUS Healthcare",
    "referringName": "Acanfora DC, Michael"
  },
  {
    "appointmentId": 76180,
    "patientId": 311322,
    "startDate": "06/26/2023  8:30AM",
    "endDate": "06/26/2023  8:45AM",
    "resourceName": "Adkins MD, Stanley",
    "description": "Walk-In",
    "status": "Checked-In",
    "insertUserId": "!gferrer",
    "insertDate": "06/26/2023  8:30AM",
    "updateUserId": "!gferrer",
    "updateDate": "06/26/2023  8:30AM",
    "comments": null,
    "referralNumber": null,
    "chiefComplaint": "",
    "claimId": 31171,
    "type": null,
    "cancelComment": null,
    "walkIn": "Y",
    "serviceLocationName": "Neighborhood Physicians Practice",
    "referringName": "Acanfora DC, Michael"
  },
  {
    "appointmentId": 76188,
    "patientId": 311322,
    "startDate": "08/07/2023 12:00PM",
    "endDate": "08/07/2023 12:20PM",
    "resourceName": "Brooks MD, Kristi F.",
    "description": "account, test F. (CKCC)",
    "status": "Scheduled",
    "insertUserId": "!gferrer",
    "insertDate": "07/06/2023 10:38AM",
    "updateUserId": "!gferrer",
    "updateDate": "07/06/2023 10:38AM",
    "comments": "Physical with a lot more information to see what it looks like",
    "referralNumber": null,
    "chiefComplaint": "Chart# 311322 - future appt test w last GFR < 20",
    "claimId": null,
    "type": "20 Min Slot",
    "cancelComment": null,
    "walkIn": null,
    "serviceLocationName": "AAOE 1",
    "referringName": "Acanfora DC, Michael"
  },
  {
    "appointmentId": 76198,
    "patientId": 311322,
    "startDate": "07/11/2023  5:00PM",
    "endDate": "07/11/2023  5:30PM",
    "resourceName": "Adkins MD, Stanley",
    "description": "account, test F. (CKCC)",
    "status": "Scheduled",
    "insertUserId": "!chandler",
    "insertDate": "07/11/2023  2:19PM",
    "updateUserId": "!chandler",
    "updateDate": "07/11/2023  2:19PM",
    "comments": "test",
    "referralNumber": null,
    "chiefComplaint": null,
    "claimId": null,
    "type": "30 Min Slot",
    "cancelComment": null,
    "walkIn": null,
    "serviceLocationName": "AAOE 1 X",
    "referringName": "Acanfora DC, Michael"
  },
  {
    "appointmentId": 76275,
    "patientId": 311322,
    "startDate": "08/01/2023 12:00AM",
    "endDate": "08/01/2023 12:10AM",
    "resourceName": "Blake, Donna",
    "description": "account, test F. (CKCC)",
    "status": "Scheduled",
    "insertUserId": "umar",
    "insertDate": "07/28/2023  4:59PM",
    "updateUserId": "umar",
    "updateDate": "07/28/2023  4:59PM",
    "comments": "this is a 10 minute comment",
    "referralNumber": null,
    "chiefComplaint": null,
    "claimId": null,
    "type": "10 Min Slots",
    "cancelComment": null,
    "walkIn": null,
    "serviceLocationName": "St Vincents Hospital",
    "referringName": "Acanfora DC, Michael"
  },
  {
    "appointmentId": 77651,
    "patientId": 311322,
    "startDate": "10/11/2023  2:00PM",
    "endDate": "10/11/2023  2:15PM",
    "resourceName": "Clark MD, ANDREA M.",
    "description": "account, test F. (CKCC)",
    "status": "Checked-Out",
    "insertUserId": "!gferrer",
    "insertDate": "10/09/2023  9:53AM",
    "updateUserId": "!gferrer",
    "updateDate": "10/11/2023  5:57PM",
    "comments": null,
    "referralNumber": null,
    "chiefComplaint": "For NEPH reporting",
    "claimId": 31223,
    "type": "15 Min Slot",
    "cancelComment": null,
    "walkIn": null,
    "serviceLocationName": "Neighborhood Physicians Practice",
    "referringName": "Acanfora DC, Michael"
  },
  {
    "appointmentId": 77652,
    "patientId": 311322,
    "startDate": "11/08/2023  1:00PM",
    "endDate": "11/08/2023  1:15PM",
    "resourceName": "Clark MD, ANDREA M.",
    "description": "account, test F. (CKCC)",
    "status": "Scheduled",
    "insertUserId": "!gferrer",
    "insertDate": "10/09/2023  9:54AM",
    "updateUserId": "!gferrer",
    "updateDate": "10/09/2023  9:54AM",
    "comments": null,
    "referralNumber": null,
    "chiefComplaint": "For NEPH reporting",
    "claimId": null,
    "type": "15 Min Slot",
    "cancelComment": null,
    "walkIn": null,
    "serviceLocationName": "Neighborhood Physicians Practice",
    "referringName": "Acanfora DC, Michael"
  },
  {
    "appointmentId": 77653,
    "patientId": 311322,
    "startDate": "12/27/2023 11:00AM",
    "endDate": "12/27/2023 11:15AM",
    "resourceName": "Clark MD, ANDREA M.",
    "description": "account, test F. (CKCC)",
    "status": "Scheduled",
    "insertUserId": "!gferrer",
    "insertDate": "10/09/2023  9:54AM",
    "updateUserId": "!gferrer",
    "updateDate": "10/09/2023  9:54AM",
    "comments": null,
    "referralNumber": null,
    "chiefComplaint": "For NEPH reporting",
    "claimId": null,
    "type": "15 Min Slot",
    "cancelComment": null,
    "walkIn": null,
    "serviceLocationName": "Neighborhood Physicians Practice",
    "referringName": "Acanfora DC, Michael"
  },
  {
    "appointmentId": 77654,
    "patientId": 311322,
    "startDate": "01/31/2024  9:00AM",
    "endDate": "01/31/2024  9:15AM",
    "resourceName": "Clark MD, ANDREA M.",
    "description": "account, test F. (CKCC)",
    "status": "Scheduled",
    "insertUserId": "!gferrer",
    "insertDate": "10/09/2023  9:55AM",
    "updateUserId": "!gferrer",
    "updateDate": "10/10/2023  4:25PM",
    "comments": "Adding a really long comment to this patient\u0027s appointment with some special characters to see if I can replicate the error being reported by i993 that generates an error in Case Mgmt when trying to open Appointment History []/?. that\u0027s \u0027pretty\u0027 much it",
    "referralNumber": null,
    "chiefComplaint": "CCM every 3 mo normally- but coordinate this month. Pt has apt in Jan- need to follow up after.",
    "claimId": null,
    "type": "15 Min Slot",
    "cancelComment": null,
    "walkIn": null,
    "serviceLocationName": "Neighborhood Physicians Practice",
    "referringName": "Acanfora DC, Michael"
  },
  {
    "appointmentId": 77670,
    "patientId": 311322,
    "startDate": "10/16/2023  8:00PM",
    "endDate": "10/16/2023  8:10PM",
    "resourceName": "Bell, Katrina",
    "description": "account, test F. (CKCC)",
    "status": "Scheduled",
    "insertUserId": "cdaoud",
    "insertDate": "10/16/2023  4:14PM",
    "updateUserId": "cdaoud",
    "updateDate": "10/16/2023  4:14PM",
    "comments": "this is a 10 minute comment",
    "referralNumber": null,
    "chiefComplaint": null,
    "claimId": null,
    "type": "10 Min Slots",
    "cancelComment": null,
    "walkIn": null,
    "serviceLocationName": "St Vincents Hospital",
    "referringName": "Acanfora DC, Michael"
  },
  {
    "appointmentId": 77723,
    "patientId": 311322,
    "startDate": "10/23/2023  5:30PM",
    "endDate": "10/23/2023  5:45PM",
    "resourceName": "Smith M.D., Gregory A.",
    "description": "account, test F. (CKCC)",
    "status": "Scheduled",
    "insertUserId": "!cdaoud",
    "insertDate": "10/23/2023  2:31PM",
    "updateUserId": "!cdaoud",
    "updateDate": "10/23/2023  2:31PM",
    "comments": null,
    "referralNumber": null,
    "chiefComplaint": null,
    "claimId": null,
    "type": "15 Min Slot",
    "cancelComment": null,
    "walkIn": null,
    "serviceLocationName": "AAOE 1",
    "referringName": "Acanfora DC, Michael"
  },
  {
    "appointmentId": 77724,
    "patientId": 311322,
    "startDate": "10/23/2023  5:30PM",
    "endDate": "10/23/2023  5:45PM",
    "resourceName": "Smith M.D., Gregory A.",
    "description": "account, test F. (CKCC)",
    "status": "Scheduled",
    "insertUserId": "!cdaoud",
    "insertDate": "10/23/2023  2:31PM",
    "updateUserId": "!cdaoud",
    "updateDate": "10/23/2023  2:31PM",
    "comments": null,
    "referralNumber": null,
    "chiefComplaint": null,
    "claimId": null,
    "type": "15 Min Slot",
    "cancelComment": null,
    "walkIn": null,
    "serviceLocationName": "AAOE 1",
    "referringName": "Acanfora DC, Michael"
  }
]